Dall_ALSA/ALSA.py
Dall_ALSA/__init__.py
Dall_ALSA/openfunctions_utils.py
Dall_ALSA/utils/__init__.py
Dall_ALSA/utils/java_parser.py
Dall_ALSA/utils/js_parser.py
Dall_ALSA/utils/python_parser.py
Dall_ALSA-0.0.3.dist-info/METADATA
Dall_ALSA-0.0.3.dist-info/WHEEL
Dall_ALSA-0.0.3.dist-info/top_level.txt
Dall_ALSA-0.0.3.dist-info/RECORD
