Metadata-Version: 2.1
Name: Dall_ALSA
Version: 0.0.3
Summary: This package does Aspect Level Sentiment Analysis on user comments 
Author: Mostafa Amiri
Author-email: <mostafa.amiri.62@gmail.com>
Keywords: python,ALSA,dall company
Classifier: Programming Language :: Python :: 3
Classifier: License :: OSI Approved :: MIT License
Classifier: Operating System :: OS Independent
Requires-Dist: tree-sitter
Requires-Dist: torch
Requires-Dist: transformers
Requires-Dist: pandas
Requires-Dist: googletrans ==3.1.0a0
Requires-Dist: tqdm
Requires-Dist: regex
